xyz_parse-0.1.4.dist-info/METADATA
xyz_parse-0.1.4.dist-info/WHEEL
xyz_parse/__init__.py
xyz_parse/xyz_parse.pyd
xyz_parse-0.1.4.dist-info/RECORD
