Metadata-Version: 2.3
Name: xyz-parse
Version: 0.1.4
Classifier: Programming Language :: Rust
Classifier: Programming Language :: Python :: Implementation :: CPython
Classifier: Programming Language :: Python :: Implementation :: PyPy
Summary: Simple parser for the XYZ file format
Keywords: xyz,chemistry,parser,parse
Home-Page: https://github.com/aqora-io/xyz-parse
Author: Julian Popescu <jpopesculian@gmail.com>
Author-email: Julian Popescu <jpopesculian@gmail.com>
License: MIT OR Apache-2.0
Requires-Python: >=3.8
Project-URL: Source Code, https://github.com/aqora-io/xyz-parse
